balaban/JosefinSans-Regular.ttf
balaban/__init__.py
balaban/balaban.py
balaban/utils.py
balaban-0.0.23.dist-info/METADATA
balaban-0.0.23.dist-info/WHEEL
balaban-0.0.23.dist-info/top_level.txt
balaban-0.0.23.dist-info/RECORD
