Metadata-Version: 2.1
Name: balaban
Version: 0.0.23
Summary: Bayesian hierarchical models for football
Home-page: https://github.com/anenglishgoat/balaban
Author: Will Thomson
Author-email: willthomson1991@gmail.com
License: UNKNOWN
Platform: UNKNOWN
Classifier: Programming Language :: Python :: 3
Classifier: License :: OSI Approved :: MIT License
Classifier: Operating System :: OS Independent
Requires-Python: >=3.2
Requires-Dist: importlib.resources
Requires-Dist: numpy
Requires-Dist: pymc3
Requires-Dist: pandas
Requires-Dist: matplotlib
Requires-Dist: selenium
